ephemera/__init__.py
Ephemera-0.0a0.dist-info/AUTHORS.md
Ephemera-0.0a0.dist-info/LICENSE.txt
Ephemera-0.0a0.dist-info/METADATA
Ephemera-0.0a0.dist-info/WHEEL
Ephemera-0.0a0.dist-info/top_level.txt
Ephemera-0.0a0.dist-info/RECORD
